CHANGES.txt
LICENSE.txt
README.txt
bootstrap.py
buildout.cfg
setup.py
src/grokcore/__init__.py
src/grokcore.registries.egg-info/PKG-INFO
src/grokcore.registries.egg-info/SOURCES.txt
src/grokcore.registries.egg-info/dependency_links.txt
src/grokcore.registries.egg-info/namespace_packages.txt
src/grokcore.registries.egg-info/not-zip-safe
src/grokcore.registries.egg-info/requires.txt
src/grokcore.registries.egg-info/top_level.txt
src/grokcore/registries/README.txt
src/grokcore/registries/__init__.py
src/grokcore/registries/components.py
src/grokcore/registries/configure.zcml
src/grokcore/registries/ftesting.zcml
src/grokcore/registries/interfaces.py
src/grokcore/registries/meta.py
src/grokcore/registries/meta.zcml
src/grokcore/registries/utils.py
src/grokcore/registries/ftests/__init__.py
src/grokcore/registries/ftests/test_grok_functional.py
src/grokcore/registries/ftests/registries/__init__.py
src/grokcore/registries/ftests/registries/basic.py
src/grokcore/registries/ftests/registries/creation.py
src/grokcore/registries/ftests/registries/grok_integration.py
src/grokcore/registries/ftests/registries/utils.py
src/grokcore/registries/tests/__init__.py
src/grokcore/registries/tests/test_doc.py
src/grokcore/registries/tests/registries/__init__.py
src/grokcore/registries/tests/registries/base.py
src/grokcore/registries/tests/registries/global.py
src/grokcore/registries/tests/registries/interfaces.py
src/grokcore/registries/tests/registries/local.py