Metadata-Version: 1.1
Name: grokcore.registries
Version: 0.1
Summary: Advanced Registry Behavior for Grok.
Home-page: http://grok.zope.org
Author: Grok Team
Author-email: grok-dev@zope.org
License: ZPL
Download-URL: http://cheeseshop.python.org/pypi/grokcore.registries/
Platform: UNKNOWN
Classifier: Environment :: Web Environment
Classifier: Intended Audience :: Developers
Classifier: License :: OSI Approved :: Zope Public License
Classifier: Programming Language :: Python
Classifier: Framework :: Zope3
